piktok/__init__.py
piktok/base.py
piktok/discover.py
piktok/info.py
piktok/stealth.py
piktok/suggested.py
piktok/tiktoks.py
piktok/verifier.py
piktok-0.1.7.dist-info/LICENSE
piktok-0.1.7.dist-info/METADATA
piktok-0.1.7.dist-info/WHEEL
piktok-0.1.7.dist-info/top_level.txt
piktok-0.1.7.dist-info/RECORD
