Metadata-Version: 2.1
Name: piktok
Version: 0.1.7
Summary: A fast module to retrieve data from TikTok
Home-page: https://github.com/anh-chu/piktok
Author: Anh Chu
Author-email: chuducanh.atred@gmail.com
License: UNKNOWN
Platform: UNKNOWN
Classifier: Programming Language :: Python :: 3
Classifier: License :: OSI Approved :: MIT License
Classifier: Operating System :: OS Independent
Requires-Python: >=3.6
Requires-Dist: requests
Requires-Dist: orjson
Requires-Dist: aiohttp
Requires-Dist: pyhumps
Requires-Dist: inflection
Requires-Dist: jmespath
Requires-Dist: pyppeteer
Requires-Dist: colored
Requires-Dist: tqdm
